knada_bq_connector/__init__.py
knada_bq_connector/bq_connector.py
knada_bq_connector-0.0.5.dist-info/METADATA
knada_bq_connector-0.0.5.dist-info/WHEEL
knada_bq_connector-0.0.5.dist-info/top_level.txt
knada_bq_connector-0.0.5.dist-info/RECORD
