Metadata-Version: 2.1
Name: knada-bq-connector
Version: 0.0.5
Summary: Python package wrapping for execute queries in BigQuery.
Home-page: UNKNOWN
Author: NAV IKT
License: MIT
Project-URL: Bug Tracker, https://github.com/navikt
Project-URL: Documentation, https://github.com/navikt
Project-URL: Source Code, https://github.com/navikt
Platform: UNKNOWN
Classifier: Development Status :: 3 - Alpha
Classifier: License :: OSI Approved :: MIT License
Classifier: Programming Language :: Python :: 3.6
Classifier: Programming Language :: Python :: 3.7
Requires-Python: >=3.6
Requires-Dist: google-auth (>=1.32.0)
Requires-Dist: google-cloud-bigquery (>=2.20.0)
Requires-Dist: pandas
